ortho_editor/__init__.py
ortho_editor/app_state.py
ortho_editor/custom_graphics_view.py
ortho_editor/drawing_app.py
ortho_editor/editor.py
ortho_editor/image_processor.py
ortho_editor/image_utils.py
ortho_editor/ui_components.py
ortho_editor/undo_manager.py
ortho_editor/fonts/MaterialIcons-Regular.ttf
ortho_editor-0.1.14.dist-info/LICENSE
ortho_editor-0.1.14.dist-info/METADATA
ortho_editor-0.1.14.dist-info/WHEEL
ortho_editor-0.1.14.dist-info/entry_points.txt
ortho_editor-0.1.14.dist-info/top_level.txt
ortho_editor-0.1.14.dist-info/RECORD
