Metadata-Version: 2.2
Name: ortho-editor
Version: 0.1.14
Summary: ORTHO mask editor tool
Home-page: https://github.com/yaacov/ortho-editor
Author: yaacov
Author-email: kobi.zamir@gmail.com
Classifier: Programming Language :: Python :: 3
Classifier: License :: OSI Approved :: MIT License
Classifier: Operating System :: OS Independent
Requires-Python: >=3.6
License-File: LICENSE
Requires-Dist: black
Requires-Dist: flake8
Requires-Dist: PyQt5
Dynamic: author
Dynamic: author-email
Dynamic: classifier
Dynamic: description
Dynamic: description-content-type
Dynamic: home-page
Dynamic: requires-dist
Dynamic: requires-python
Dynamic: summary
